{
    "DiffusionScheme": "Bipolar",
    "EchoTime": 0.089,
    "FlipAngle": 90,
    "MultibandAccelerationFactor": 2,
    "PartialFourier": 0.875,
    "PhaseEncodingDirection": "j",
    "PixelBandwidth": 1655,
    "RepetitionTime": 4.4,
    "SliceEncodingDirection": "k-",
    "SliceTiming": [
        2.1275,
        0.0,
        2.2525,
        0.125,
        2.3775,
        0.25,
        2.5025,
        0.375,
        2.6275,
        0.5,
        2.7525,
        0.625,
        2.8775,
        0.75,
        3.0025,
        0.875,
        3.1275,
        1.0,
        3.2525,
        1.125,
        3.3775,
        1.25,
        3.5025,
        1.375,
        3.6275,
        1.5,
        3.7525,
        1.6275,
        3.88,
        1.7525,
        4.005,
        1.8775,
        4.13,
        2.0025,
        4.255,
        2.1275,
        0.0,
        2.2525,
        0.125,
        2.3775,
        0.25,
        2.5025,
        0.375,
        2.6275,
        0.5,
        2.7525,
        0.625,
        2.8775,
        0.75,
        3.0025,
        0.875,
        3.1275,
        1.0,
        3.2525,
        1.125,
        3.3775,
        1.25,
        3.5025,
        1.375,
        3.6275,
        1.5,
        3.7525,
        1.6275,
        3.88,
        1.7525,
        4.005,
        1.8775,
        4.13,
        2.0025,
        4.255
    ],
    "TotalReadoutTime": 0.0369,
    "command_history": "mrconvert /n/gaab_mri_l3/Lab/DMC-Gaab2/hgse/BabyBOLD/PRE_BB018/diffusion/ /n/holyscratch01/LABS/gaab_mri_l3/Lab/diff_long/PRE_BB018/preproc/dwi.mif -strides '-1,-2,+3,+4' -force  (version=3.0.3)",
    "comments": [
        "102221_PRE_BB018_T3 (102221_PRE_BB018_T3) [MR] SMS2_Diff_b1000_10b0s",
        "study: Investigators^Gaab [ ORIGINAL PRIMARY DIFFUSION NONE ND NORM MOSAIC ]",
        "DOB: 01/01/2016",
        "DOS: 22/10/2021 12:56:42"
    ],
    "dw_scheme": [
        [
            0.0,
            0.0,
            0.0,
            0.0
        ],
        [
            0.0,
            0.0,
            0.0,
            0.0
        ],
        [
            0.0,
            0.0,
            0.0,
            0.0
        ],
        [
            0.0,
            0.0,
            0.0,
            0.0
        ],
        [
            0.0,
            0.0,
            0.0,
            0.0
        ],
        [
            0.0,
            0.0,
            0.0,
            0.0
        ],
        [
            0.0,
            0.0,
            0.0,
            0.0
        ],
        [
            0.0,
            0.0,
            0.0,
            0.0
        ],
        [
            0.0,
            0.0,
            0.0,
            0.0
        ],
        [
            0.0,
            0.0,
            0.0,
            0.0
        ],
        [
            0.0,
            0.0,
            0.0,
            0.0
        ],
        [
            0.2030062185,
            0.5204301718,
            -0.8294220347,
            999.9999165
        ],
        [
            -0.1970231678,
            0.5210807842,
            -0.8304557108,
            1000.000022
        ],
        [
            -0.4017973949,
            0.1769189434,
            -0.8984756763,
            1000.000075
        ],
        [
            0.4029081349,
            0.7318449926,
            -0.5496070794,
            1000.000075
        ],
        [
            0.2019627151,
            0.9417100439,
            -0.2690599468,
            999.999652
        ],
        [
            0.8519457399,
            0.5202141044,
            -0.0597138328,
            999.9999063
        ],
        [
            0.7302893745,
            0.5212848446,
            -0.4415195809,
            999.9999055
        ],
        [
            0.4061054895,
            0.1772314298,
            -0.8964749588,
            1000.000003
        ],
        [
            0.7317389668,
            0.1771212913,
            -0.6581687721,
            999.9998719
        ],
        [
            0.650551245,
            0.7316873606,
            0.2035108941,
            999.9998618
        ],
        [
            0.3222832077,
            0.9416150055,
            0.09744083023,
            1000.000201
        ],
        [
            0.3247015574,
            0.5229233736,
            0.7881116951,
            1000.000139
        ],
        [
            0.6513912543,
            0.5219818274,
            0.5506581568,
            1000.000048
        ],
        [
            0.9789215566,
            0.1777319948,
            0.1006177127,
            999.9999458
        ],
        [
            0.8564492354,
            0.178076027,
            0.4845447717,
            1000.000034
        ],
        [
            -0.000685080021,
            0.7348007825,
            0.6782826407,
            999.9999388
        ],
        [
            -0.003503069976,
            0.9436733635,
            0.3308599577,
            1000.000014
        ],
        [
            -0.6556783026,
            0.5220338482,
            0.5454966772,
            1000.000084
        ],
        [
            -0.3303012007,
            0.5233090036,
            0.7855245404,
            1000.000177
        ],
        [
            -0.197233288,
            -0.1772054562,
            -0.9642080981,
            999.9998173
        ],
        [
            -0.2047022767,
            0.1772079385,
            0.9626496374,
            1000.00013
        ],
        [
            -0.6510940784,
            0.7321456082,
            0.2000982495,
            1000.000005
        ],
        [
            -0.3242195581,
            0.9413784705,
            0.09321080094,
            999.9997652
        ],
        [
            -0.2000313075,
            0.9405509941,
            -0.2745019191,
            1000.000225
        ],
        [
            -0.4034022216,
            0.731816491,
            -0.5492825058,
            999.9999427
        ],
        [
            -0.7317389668,
            0.1771212913,
            -0.6581687721,
            999.9998719
        ],
        [
            -0.7275047595,
            0.5205273811,
            -0.4469765881,
            999.9999187
        ],
        [
            -0.8516358609,
            0.5200065944,
            -0.0656467993,
            1000.000021
        ],
        [
            -0.8592498251,
            0.1775763666,
            0.4797461538,
            1000.000151
        ],
        [
            -0.9795455034,
            0.1776797261,
            0.09444851322,
            999.9999316
        ]
    ],
    "mrtrix_version": "3.0.3"
}