{
    "EchoTime": 0.088,
    "FlipAngle": 90,
    "MultibandAccelerationFactor": 1,
    "PhaseEncodingDirection": "j",
    "PixelBandwidth": 1634,
    "RepetitionTime": 4.5,
    "SliceEncodingDirection": "k-",
    "SliceTiming": [
        0.0,
        86395.72,
        0.1225,
        86395.848,
        0.245,
        86395.968,
        0.3675,
        86396.088,
        0.49,
        86396.216,
        0.6125,
        86396.336,
        0.735,
        86396.456,
        0.855,
        86396.576,
        0.9775,
        86396.704,
        1.1,
        86396.824,
        1.2225,
        86396.944,
        1.345,
        86397.064,
        1.4675,
        86397.192,
        1.59,
        86397.312,
        1.7125,
        86397.432,
        1.835,
        86397.552,
        1.955,
        86397.68,
        2.0775,
        86397.8,
        2.2,
        86397.92,
        2.3225,
        86398.048,
        2.445,
        86398.168,
        2.5675,
        86398.288,
        2.69,
        86398.416,
        2.8125,
        86398.536,
        2.935,
        86398.656,
        3.055,
        86398.776,
        3.1775,
        86398.896,
        3.3,
        86399.024,
        3.4225,
        86399.144,
        3.545,
        86399.264,
        3.6675,
        86399.392,
        3.79,
        86399.512,
        3.9125,
        86399.632,
        4.035,
        86399.752,
        4.155,
        86399.88
    ],
    "TotalReadoutTime": 0.032,
    "command_history": "mrconvert /n/gaab_mri_l3/Lab/DMC-Gaab2/d-dcms/BabyMRI/INF_BB042_T1_20171208/DICOMS/SMS2_Diff_b1000_10b0s-SMS2_Diff_b1000_10b0s-289754 /n/holyscratch01/LABS/gaab_mri_l3/Lab/diff_long/INF_BB042/preproc/dwi.mif -strides '-1,-2,+3,+4' -force  (version=3.0.3)",
    "comments": [
        "anon (anon) [MR] SMS2_Diff_b1000_10b0s",
        "study: MR-EI Neuro [ ORIGINAL PRIMARY DIFFUSION NONE ND NORM MOSAIC ]",
        "DOB: on/an/anon",
        "DOS: anon 21:28:28"
    ],
    "dw_scheme": [
        [
            0.0,
            0.0,
            0.0,
            0.0
        ],
        [
            0.0,
            0.0,
            0.0,
            0.0
        ],
        [
            0.0,
            0.0,
            0.0,
            0.0
        ],
        [
            0.0,
            0.0,
            0.0,
            0.0
        ],
        [
            0.0,
            0.0,
            0.0,
            0.0
        ],
        [
            0.0,
            0.0,
            0.0,
            0.0
        ],
        [
            0.0,
            0.0,
            0.0,
            0.0
        ],
        [
            0.0,
            0.0,
            0.0,
            0.0
        ],
        [
            0.0,
            0.0,
            0.0,
            0.0
        ],
        [
            0.0,
            0.0,
            0.0,
            0.0
        ],
        [
            0.2007315326,
            0.5155697823,
            -0.8330033922,
            999.9998747
        ],
        [
            -0.196106209,
            0.5157542774,
            -0.8339903358,
            1000.00001
        ],
        [
            -0.3983142514,
            0.175095805,
            -0.9003817058,
            999.9999425
        ],
        [
            0.40037624,
            0.7273876228,
            -0.5573204757,
            999.9997998
        ],
        [
            0.2004526798,
            0.9392695463,
            -0.2785524053,
            999.9996031
        ],
        [
            0.8517049187,
            0.5194404814,
            -0.06913984152,
            999.9999559
        ],
        [
            0.7272608551,
            0.5179929879,
            -0.4503053555,
            999.9999312
        ],
        [
            0.4016184669,
            0.1745149673,
            -0.8990256577,
            999.9999161
        ],
        [
            0.726491355,
            0.175549957,
            -0.6643737831,
            1000.000262
        ],
        [
            0.651423036,
            0.733136483,
            0.1953430968,
            999.9998281
        ],
        [
            0.3216696235,
            0.9426050918,
            0.08957842541,
            1000.000102
        ],
        [
            0.3267870846,
            0.5266327974,
            0.784772641,
            949.9999734
        ],
        [
            0.6545555845,
            0.5243608477,
            0.5446124203,
            999.9997421
        ],
        [
            0.9799049902,
            0.1769570373,
            0.09204573378,
            999.9999179
        ],
        [
            0.8601226224,
            0.1778284781,
            0.478085878,
            1000.000134
        ],
        [
            -0.002141850087,
            0.7390460101,
            0.6736515475,
            999.9999185
        ],
        [
            -0.003530719797,
            0.9463121955,
            0.3232348414,
            1000.000115
        ],
        [
            -0.659129188,
            0.5243217682,
            0.5391061092,
            999.9998546
        ],
        [
            -0.3332126747,
            0.5263434521,
            0.7822607518,
            949.9996313
        ],
        [
            -0.1939383369,
            -0.1744199042,
            -0.9653836639,
            999.9997226
        ],
        [
            -0.2071691502,
            0.1788885102,
            0.9618107112,
            949.9999978
        ],
        [
            -0.6526599559,
            0.732702624,
            0.1928259495,
            999.9997982
        ],
        [
            -0.3248608336,
            0.9419320614,
            0.08502605832,
            1000.00004
        ],
        [
            -0.1994466806,
            0.9379136418,
            -0.2837939782,
            1000.000295
        ],
        [
            -0.4016919079,
            0.7272262505,
            -0.5565838587,
            999.9998612
        ],
        [
            -0.726825369,
            0.1761394576,
            -0.6638522234,
            1000.00014
        ],
        [
            -0.7247403702,
            0.5175508759,
            -0.4548543576,
            1000.000055
        ],
        [
            -0.8515208029,
            0.5188735839,
            -0.07538253203,
            999.9999462
        ],
        [
            -0.8629311371,
            0.1779982791,
            0.472933891,
            1000.000123
        ],
        [
            -0.9803823422,
            0.177098944,
            0.08652414196,
            999.9999547
        ]
    ],
    "mrtrix_version": "3.0.3"
}